setup.cfg
setup.py
pymeboot/__init__.py
pymeboot/meboot.py
pymeboot.egg-info/PKG-INFO
pymeboot.egg-info/SOURCES.txt
pymeboot.egg-info/dependency_links.txt
pymeboot.egg-info/top_level.txt