Metadata-Version: 1.1
Name: pymeboot
Version: 0.0.1.post1
Summary: Maximum entropy bootstrap for time series
Home-page: https://github.com/kirahg/pymeboot
Author: Kira Huselius Gylling
Author-email: kira.gylling@gmail.com
License: MIT
Download-URL: https://github.com/kirahg/pymeboot/tarball/0.0.1-1
Keywords: data,statistics,time series,bootstrap
Platform: UNKNOWN
